facilenewbusinesslib/__init__.py
facilenewbusinesslib/facilenewbusinesslib.py
facile_new_business_lib-0.0.8.dist-info/METADATA
facile_new_business_lib-0.0.8.dist-info/WHEEL
facile_new_business_lib-0.0.8.dist-info/top_level.txt
facile_new_business_lib-0.0.8.dist-info/RECORD
