Metadata-Version: 2.1
Name: facile-new-business-lib
Version: 0.0.8
Summary: testing 
Home-page: https://www.facile.it
Author: Fabio Lima
Author-email: f46io@icloud.com
License: UNKNOWN
Platform: UNKNOWN
Requires-Dist: selenium (~=3.141.0)
Requires-Dist: robotframework (~=3.2)
